{
  "args": {},
  "desc": "Returns search capabilities on a given team.",
  "errors": {},
  "rate_limit": {
    "label": "Tier 2: 20+ per minute",
    "url": "https://docs.slack.dev/apis/web-api/rate-limits"
  },
  "scopes": {
    "bot": [
      {
        "name": "search:read.public",
        "url": "https://docs.slack.dev/reference/scopes/search.read.public"
      }
    ],
    "user": [
      {
        "name": "search:read.public",
        "url": "https://docs.slack.dev/reference/scopes/search.read.public"
      }
    ]
  }
}

