{
  "args": {
    "duration": {
      "desc": "Call duration in seconds",
      "example": "1800",
      "required": false,
      "type": "integer"
    },
    "id": {
      "desc": "`id` returned when registering the call using the `calls.add` method.",
      "example": "R0E69JAIF",
      "required": true,
      "type": "string"
    }
  },
  "desc": "Ends a Call.",
  "errors": {
    "inactive_call": "The Call has been already stopped.",
    "invalid_call_id": "Invalid Call ID.",
    "not_implemented": "This method is not publicly available yet."
  },
  "rate_limit": {
    "label": "Tier 3: 50+ per minute",
    "url": "https://docs.slack.dev/apis/web-api/rate-limits"
  },
  "scopes": {
    "bot": [
      {
        "name": "calls:write",
        "url": "https://docs.slack.dev/reference/scopes/calls.write"
      }
    ],
    "user": [
      {
        "name": "calls:write",
        "url": "https://docs.slack.dev/reference/scopes/calls.write"
      }
    ]
  }
}

